pdbinf/__init__.py
pdbinf/_compress.py
pdbinf/_dna_bases.py
pdbinf/_pdbinf.py
pdbinf/_rna_bases.py
pdbinf/_standard_AAs.py
pdbinf/tests/conftest.py
pdbinf/tests/test_181L.py
pdbinf/tests/test_compress.py
pdbinf/tests/test_dna.py
pdbinf/tests/test_nonstandard.py
pdbinf/tests/test_nucleic.py
pdbinf/tests/test_openmm_regression.py
pdbinf/tests/test_pdbx_support.py
pdbinf/tests/test_rna.py
pdbinf/tests/test_standard_AAs.py
pdbinf/tests/test_thrombin.py
pdbinf-0.0.4.dist-info/LICENSE
pdbinf-0.0.4.dist-info/METADATA
pdbinf-0.0.4.dist-info/WHEEL
pdbinf-0.0.4.dist-info/top_level.txt
pdbinf-0.0.4.dist-info/RECORD
