Metadata-Version: 2.1
Name: pdbinf
Version: 0.0.4
Summary: Load PDB files into rdkit with nonstandard residues
Author-email: Richard J Gowers <richardjgowers@gmail.com>
Project-URL: Homepage, https://github.com/OpenFreeEnergy/pdbinf
Project-URL: Bug Tracker, https://github.com/OpenFreeEnergy/pdbinf/issues
Classifier: Programming Language :: Python :: 3
Classifier: License :: OSI Approved :: MIT License
Classifier: Operating System :: OS Independent
Requires-Python: >=3.9
License-File: LICENSE
Requires-Dist: rdkit
Requires-Dist: gemmi
Requires-Dist: numpy
Provides-Extra: tests
Requires-Dist: pytest ; extra == 'tests'
Requires-Dist: pytest-cov ; extra == 'tests'
Requires-Dist: coverage ; extra == 'tests'
Requires-Dist: pooch ; extra == 'tests'
